<?xml version="1.0" encoding="UTF-8"?>
<entities do-package="com.dianping.cat.web" gen="true">
	<entity name="js-error-log" table="js_error_log" alias="jel">
	   	<member name="modules" value-type="String" all="false" select-expr="distinct module" length="19" nullable="false" />
	    <member name="count" value-type="long" all="false" select-expr="count(*)" length="19" nullable="false" />
	    <var name="start-time" value-type="Date" />
	    <var name="end-time" value-type="Date" />
	    <var name="offset" value-type="int" />
	   	<var name="limit" value-type="int" />
		<readsets>
      	<readset name="DISTINCT_MODULES">
      		<member name="modules"/>
      	</readset>
      	<readset name="COUNT-DATA">
      		<member name="count"/>
      		<member name="module"/>
      		<member name="level"/>
      	</readset>
      	</readsets>
		<query-defs>
		<query name="insert" type="INSERT" batch="true">
			<statement><![CDATA[INSERT INTO <TABLE/>(<FIELDS/>)
        VALUES(<VALUES/>)]]></statement>
		</query>
		<query name="find-data-by-time-module-level-browser" type="SELECT" multiple="true">
			<param name="start-time" />
			<param name="end-time" />
			<param name="module" />
			<param name="level" />
			<param name="browser" />
			<param name="dpid" />
			<param name="offset" />
			<param name="limit" />
			<statement><![CDATA[SELECT <FIELDS/>
        FROM <TABLE/>
        WHERE <FIELD name='error-time'/> >= ${start-time} 
			AND  <FIELD name='error-time'/> < ${end-time}
        <IF type='NOT_NULL' field='module'>
			AND  <FIELD name='module'/> = ${module}
		</IF>
		<IF type='NE' field='level' value='-1'>
			AND  <FIELD name='level'/> = ${level}
		</IF>
		<IF type='NOT_NULL' field='browser'>
			AND  <FIELD name='browser'/> = ${browser}
		</IF>
		<IF type='NOT_NULL' field='dpid'>
			AND  <FIELD name='dpid'/> = ${dpid}
		</IF>
		LIMIT ${offset}, ${limit}
         ]]></statement>
		</query>
		<query name="find-count-by-time-module-level" type="SELECT" multiple="true">
			<param name="start-time" />
			<param name="end-time" />
		<statement><![CDATA[SELECT <FIELDS/>
        	FROM <TABLE/>
        	  WHERE <FIELD name='error-time'/> >= ${start-time} 
			AND  <FIELD name='error-time'/> < ${end-time}
			GROUP BY module, level
         ]]></statement>
		</query>
		<query name="find-modules" type="SELECT" multiple="true">
		<statement><![CDATA[SELECT <FIELDS/>
        	FROM <TABLE/>
         ]]></statement>
		</query>
		<query name="delete-before-period" type="DELETE">
        <param name="updatetime" />
        <statement><![CDATA[DELETE FROM <TABLE/>
        WHERE <FIELD name='updatetime'/> <= ${updatetime}]]></statement>
      </query>
		</query-defs>
	</entity>
	<entity name="js-error-log-content" table="js_error_log_content"
		alias="jelc">
		<query-defs>
		<query name="insert" type="INSERT" batch="true">
			<statement><![CDATA[INSERT INTO <TABLE/>(<FIELDS/>)
        VALUES(<VALUES/>)]]></statement>
		</query>
		<query name="delete-before-period" type="DELETE">
        <param name="updatetime" />
        <statement><![CDATA[DELETE FROM <TABLE/>
        WHERE <FIELD name='updatetime'/> <= ${updatetime}]]></statement>
      </query>
		</query-defs>
	</entity>
	<entity name="ajax-data" table="ajax_data" alias="ad">
		<member name="access-number-sum" value-type="long" all="false"
			select-expr="sum(access_number)" length="19" nullable="false" />
		<member name="response-sum-time-sum" value-type="long" all="false"
			select-expr="sum(response_sum_time)" length="19" nullable="false" />
		<member name="request-sum-byte-sum" value-type="long" all="false"
			select-expr="sum(request_sum_byte)" length="19" nullable="false" />
		<member name="response-sum-byte-sum" value-type="long" all="false"
			select-expr="sum(response_sum_byte)" length="19" nullable="false" />
		<var name="api-id" value-type="int" />
		<var name="start-minute-order" value-type="int" />
		<var name="end-minute-order" value-type="int" />
		<readsets>
			<readset name="COUNT-DATA">
				<member name="minute-order" />
				<member name="access-number-sum" />
			</readset>
			<readset name="AVG-DATA">
				<member name="minute-order" />
				<member name="access-number-sum" />
				<member name="response-sum-time-sum" />
			</readset>
			<readset name="REQUEST-BYTE-AVG-DATA">
				<member name="minute-order" />
				<member name="access-number-sum" />
				<member name="request-sum-byte-sum" />
			</readset>
			<readset name="RESPONSE-BYTE-AVG-DATA">
				<member name="minute-order" />
				<member name="access-number-sum" />
				<member name="response-sum-byte-sum" />
			</readset>
			<readset name="SUCCESS-DATA">
				<member name="minute-order" />
				<member name="code" />
				<member name="access-number-sum" />
			</readset>
			<readset name="CODE-DATA">
				<member name="code" />
				<member name="access-number-sum" />
				<member name="response-sum-time-sum" />
				<member name="request-sum-byte-sum" />
				<member name="response-sum-byte-sum" />
			</readset>
			<readset name="OPERATOR-DATA">
				<member name="operator" />
				<member name="access-number-sum" />
				<member name="response-sum-time-sum" />
			</readset>
				<readset name="OPERATOR-CODE-DATA">
				<member name="code" />
				<member name="operator" />
				<member name="access-number-sum" />
				<member name="response-sum-time-sum" />
				<member name="request-sum-byte-sum" />
				<member name="response-sum-byte-sum" />
			</readset>
			<readset name="CITY-DATA">
				<member name="city" />
				<member name="access-number-sum" />
				<member name="response-sum-time-sum" />
			</readset>
			<readset name="CITY-CODE-DATA">
				<member name="code" />
				<member name="city" />
				<member name="access-number-sum" />
				<member name="response-sum-time-sum" />
				<member name="request-sum-byte-sum" />
				<member name="response-sum-byte-sum" />
			</readset>
			<readset name="NETWORK-DATA">
				<member name="network" />
				<member name="access-number-sum" />
				<member name="response-sum-time-sum" />
			</readset>
			<readset name="NETWORK-CODE-DATA">
				<member name="code" />
				<member name="network" />
				<member name="access-number-sum" />
				<member name="response-sum-time-sum" />
				<member name="request-sum-byte-sum" />
				<member name="response-sum-byte-sum" />
			</readset>
		</readsets>
		<query-defs>
			<query name="insert" type="INSERT" batch="true">
				<statement><![CDATA[INSERT INTO <TABLE/>(<FIELDS/>)
        VALUES(<VALUES/>)]]></statement>
			</query>
			<query name="insert-or-update" type="INSERT" batch="true">
				<statement><![CDATA[INSERT INTO <TABLE/>(<FIELDS/>)
        VALUES(<VALUES/>) ON DUPLICATE KEY UPDATE 
        access_number = access_number + ${access-number},
        response_sum_time = response_sum_time + ${response-sum-time},
        request_sum_byte = request_sum_byte + ${request-sum-byte},
        response_sum_byte = response_sum_byte + ${response-sum-byte}
         ]]></statement>
			</query>
			<query name="delete-before-period" type="DELETE">
				<param name="period" />
				<statement><![CDATA[DELETE FROM <TABLE/>
        WHERE <FIELD name='period'/> <= ${period}]]></statement>
			</query>
			<query name="find-data-by-minute" type="SELECT" multiple="true">
				<param name="api-id" />
				<param name="period" />
				<param name="city" />
				<param name="operator" />
				<param name="code" />
				<param name="network" />
				<param name="start-minute-order" />
				<param name="end-minute-order" />
				<statement><![CDATA[SELECT <FIELDS/>
        FROM <TABLE/>
        WHERE <FIELD name='period'/> = ${period} 
        <IF type='NE' field='start-minute-order' value='-1'>
			AND  <FIELD name='minute-order'/> >= ${start-minute-order}
		</IF>
		<IF type='NE' field='end-minute-order' value='-1'>
			AND  <FIELD name='minute-order'/> <= ${end-minute-order}
		</IF> 
        <IF type='NE' field='city' value='-1'>
			AND  <FIELD name='city'/> = ${city}
		</IF>
        <IF type='NE' field='operator' value='-1'>
			AND  <FIELD name='operator'/> = ${operator}
		</IF>
		<IF type='NE' field='code' value='-1'>
			AND  <FIELD name='code'/> = ${code}
		</IF>
		<IF type='NE' field='network' value='-1'>
			AND  <FIELD name='network'/> = ${network}
		</IF>
        group by  <FIELD name='minute-order'/>  ]]></statement>
			</query>
			<query name="find-daily-data-by-code" type="SELECT" multiple="true">
				<param name="api-id" />
				<param name="period" />
				<statement><![CDATA[SELECT <FIELDS/>
        FROM <TABLE/>
        WHERE <FIELD name='period'/> = ${period} 
        group by <FIELD name='code'/>  ]]></statement>
			</query>
			<query name="find-data-by-minute-code" type="SELECT" multiple="true">
				<param name="api-id" />
				<param name="period" />
				<param name="city" />
				<param name="operator" />
				<param name="code" />
				<param name="network" />
				<param name="start-minute-order" />
				<param name="end-minute-order" />
				<statement><![CDATA[SELECT <FIELDS/>
        FROM <TABLE/>
        WHERE <FIELD name='period'/> = ${period} 
        <IF type='NE' field='start-minute-order' value='-1'>
			AND  <FIELD name='minute-order'/> >= ${start-minute-order}
		</IF>
		<IF type='NE' field='end-minute-order' value='-1'>
			AND  <FIELD name='minute-order'/> <= ${end-minute-order}
		</IF> 
        <IF type='NE' field='city' value='-1'>
			AND  <FIELD name='city'/> = ${city}
		</IF>
        <IF type='NE' field='operator' value='-1'>
			AND  <FIELD name='operator'/> = ${operator}
		</IF> 
		<IF type='NE' field='code' value='-1'>
			AND  <FIELD name='code'/> = ${code}
		</IF>
		<IF type='NE' field='network' value='-1'>
			AND  <FIELD name='network'/> = ${network}
		</IF>
        group by  <FIELD name='minute-order'/>,<FIELD name='code'/>  ]]></statement>
			</query>
			<query name="find-data-by-code" type="SELECT" multiple="true">
				<param name="api-id" />
				<param name="period" />
				<param name="city" />
				<param name="operator" />
				<param name="code" />
				<param name="network" />
				<param name="start-minute-order" />
				<param name="end-minute-order" />
				<statement><![CDATA[SELECT <FIELDS/>
        FROM <TABLE/>
        WHERE <FIELD name='period'/> = ${period}
        <IF type='NE' field='start-minute-order' value='-1'>
			AND  <FIELD name='minute-order'/> >= ${start-minute-order}
		</IF>
		<IF type='NE' field='end-minute-order' value='-1'>
			AND  <FIELD name='minute-order'/> <= ${end-minute-order}
		</IF> 
        <IF type='NE' field='city' value='-1'>
			AND  <FIELD name='city'/> = ${city}
		</IF>
        <IF type='NE' field='operator' value='-1'>
			AND  <FIELD name='operator'/> = ${operator}
		</IF>    
		<IF type='NE' field='code' value='-1'>
			AND  <FIELD name='code'/> = ${code}
		</IF>
		<IF type='NE' field='network' value='-1'>
			AND  <FIELD name='network'/> = ${network}
		</IF>
        group by  <FIELD name='code'/> ]]></statement>
			</query>
			<query name="find-data-by-operator" type="SELECT" multiple="true">
				<param name="api-id" />
				<param name="period" />
				<param name="city" />
				<param name="operator" />
				<param name="code" />
				<param name="network" />
				<param name="start-minute-order" />
				<param name="end-minute-order" />
				<statement><![CDATA[SELECT <FIELDS/>
        FROM <TABLE/>
        WHERE <FIELD name='period'/> = ${period} 
        <IF type='NE' field='start-minute-order' value='-1'>
			AND  <FIELD name='minute-order'/> >= ${start-minute-order}
		</IF>
		<IF type='NE' field='end-minute-order' value='-1'>
			AND  <FIELD name='minute-order'/> <= ${end-minute-order}
		</IF>
		<IF type='NE' field='city' value='-1'>
			AND  <FIELD name='city'/> = ${city}
		</IF>
        <IF type='NE' field='operator' value='-1'>
			AND  <FIELD name='operator'/> = ${operator}
		</IF>       
		<IF type='NE' field='code' value='-1'>
			AND  <FIELD name='code'/> = ${code}
		</IF>		
		<IF type='NE' field='network' value='-1'>
			AND  <FIELD name='network'/> = ${network}
		</IF>
        group by  <FIELD name='operator'/>  ]]></statement>
			</query>
			<query name="find-data-by-city" type="SELECT" multiple="true">
				<param name="api-id" />
				<param name="period" />
				<param name="city" />
				<param name="operator" />
				<param name="code" />
				<param name="network" />
				<param name="start-minute-order" />
				<param name="end-minute-order" />
				<statement><![CDATA[SELECT <FIELDS/>
        FROM <TABLE/>
        WHERE <FIELD name='period'/> = ${period} 
        <IF type='NE' field='start-minute-order' value='-1'>
			AND  <FIELD name='minute-order'/> >= ${start-minute-order}
		</IF>
		<IF type='NE' field='end-minute-order' value='-1'>
			AND  <FIELD name='minute-order'/> <= ${end-minute-order}
		</IF>
        <IF type='NE' field='city' value='-1'>
			AND  <FIELD name='city'/> = ${city}
		</IF>
        <IF type='NE' field='operator' value='-1'>
			AND  <FIELD name='operator'/> = ${operator}
		</IF>     
		<IF type='NE' field='code' value='-1'>
			AND  <FIELD name='code'/> = ${code}
		</IF>
		<IF type='NE' field='network' value='-1'>
			AND  <FIELD name='network'/> = ${network}
		</IF>	
        group by  <FIELD name='city'/>  ]]></statement>
	</query>
	<query name="find-data-by-network" type="SELECT" multiple="true">
		<param name="api-id" />
		<param name="period" />
		<param name="city" />
		<param name="operator" />
		<param name="code" />
		<param name="network" />
		<param name="start-minute-order" />
		<param name="end-minute-order" />
		<statement><![CDATA[SELECT <FIELDS/>
        FROM <TABLE/>
        WHERE <FIELD name='period'/> = ${period} 
        <IF type='NE' field='start-minute-order' value='-1'>
			AND  <FIELD name='minute-order'/> >= ${start-minute-order}
		</IF>
		<IF type='NE' field='end-minute-order' value='-1'>
			AND  <FIELD name='minute-order'/> <= ${end-minute-order}
		</IF>
        <IF type='NE' field='city' value='-1'>
			AND  <FIELD name='city'/> = ${city}
		</IF>
        <IF type='NE' field='operator' value='-1'>
			AND  <FIELD name='operator'/> = ${operator}
		</IF>     
		<IF type='NE' field='code' value='-1'>
			AND  <FIELD name='code'/> = ${code}
		</IF>
		<IF type='NE' field='network' value='-1'>
			AND  <FIELD name='network'/> = ${network}
		</IF>	
        group by  <FIELD name='network'/>  ]]></statement>
			</query>
	<query name="find-data-by-operator-code" type="SELECT" multiple="true">
        <param name="api-id" />
        <param name="period" />
        <param name="city" />
        <param name="operator" />
        <param name="network" />
        <param name="code" />
        <statement><![CDATA[SELECT <FIELDS/>
        FROM <TABLE/>
        WHERE <FIELD name='period'/> = ${period} 
        <IF type='NE' field='city' value='-1'>
			AND  <FIELD name='city'/> = ${city}
		</IF>
        <IF type='NE' field='operator' value='-1'>
			AND  <FIELD name='operator'/> = ${operator}
		</IF>
        <IF type='NE' field='network' value='-1'>
			AND  <FIELD name='network'/> = ${network}
		</IF>
		<IF type='NE' field='code' value='-1'>
			AND  <FIELD name='code'/> = ${code}
		</IF>
        group by <FIELD name='operator'/>, <FIELD name='code'/>]]></statement>
      </query>
      <query name="find-data-by-network-code" type="SELECT" multiple="true">
        <param name="api-id" />
        <param name="period" />
        <param name="city" />
        <param name="operator" />
        <param name="network" />
        <param name="code" />
        <statement><![CDATA[SELECT <FIELDS/>
        FROM <TABLE/>
        WHERE <FIELD name='period'/> = ${period} 
        <IF type='NE' field='city' value='-1'>
			AND  <FIELD name='city'/> = ${city}
		</IF>
        <IF type='NE' field='operator' value='-1'>
			AND  <FIELD name='operator'/> = ${operator}
		</IF>
        <IF type='NE' field='network' value='-1'>
			AND  <FIELD name='network'/> = ${network}
		</IF>
		<IF type='NE' field='code' value='-1'>
			AND  <FIELD name='code'/> = ${code}
		</IF>
        group by <FIELD name='network'/>, <FIELD name='code'/>]]></statement>
      </query>
      <query name="find-data-by-city-code" type="SELECT" multiple="true">
        <param name="api-id" />
        <param name="period" />
        <param name="city" />
        <param name="operator" />
        <param name="network" />
        <param name="code" />
        <statement><![CDATA[SELECT <FIELDS/>
        FROM <TABLE/>
        WHERE <FIELD name='period'/> = ${period} 
        <IF type='NE' field='city' value='-1'>
			AND  <FIELD name='city'/> = ${city}
		</IF>
        <IF type='NE' field='operator' value='-1'>
			AND  <FIELD name='operator'/> = ${operator}
		</IF>
        <IF type='NE' field='network' value='-1'>
			AND  <FIELD name='network'/> = ${network}
		</IF>
		<IF type='NE' field='code' value='-1'>
			AND  <FIELD name='code'/> = ${code}
		</IF>
        group by <FIELD name='city'/>, <FIELD name='code'/>]]></statement>
      </query>
		</query-defs>
	</entity>
  	<entity name="web-speed-data" table="web_speed_data" alias="wsd">
  		<member name="access-number-sum1" value-type="long" all="false" select-expr="sum(access_number1)" length="19" nullable="false" />
   		<member name="access-number-sum2" value-type="long" all="false" select-expr="sum(access_number2)" length="19" nullable="false" />
   		<member name="access-number-sum3" value-type="long" all="false" select-expr="sum(access_number3)" length="19" nullable="false" />
   		<member name="access-number-sum4" value-type="long" all="false" select-expr="sum(access_number4)" length="19" nullable="false" />
   		<member name="access-number-sum5" value-type="long" all="false" select-expr="sum(access_number5)" length="19" nullable="false" />
   		<member name="access-number-sum6" value-type="long" all="false" select-expr="sum(access_number6)" length="19" nullable="false" />
   		<member name="access-number-sum7" value-type="long" all="false" select-expr="sum(access_number7)" length="19" nullable="false" />
   		<member name="access-number-sum8" value-type="long" all="false" select-expr="sum(access_number8)" length="19" nullable="false" />
   		<member name="access-number-sum9" value-type="long" all="false" select-expr="sum(access_number9)" length="19" nullable="false" />
   		<member name="access-number-sum10" value-type="long" all="false" select-expr="sum(access_number10)" length="19" nullable="false" />
   		<member name="access-number-sum11" value-type="long" all="false" select-expr="sum(access_number11)" length="19" nullable="false" />
   		<member name="access-number-sum12" value-type="long" all="false" select-expr="sum(access_number12)" length="19" nullable="false" />
   		<member name="access-number-sum13" value-type="long" all="false" select-expr="sum(access_number13)" length="19" nullable="false" />
   		<member name="access-number-sum14" value-type="long" all="false" select-expr="sum(access_number14)" length="19" nullable="false" />
   		<member name="access-number-sum15" value-type="long" all="false" select-expr="sum(access_number15)" length="19" nullable="false" />
   		<member name="access-number-sum16" value-type="long" all="false" select-expr="sum(access_number16)" length="19" nullable="false" />
   		<member name="access-number-sum17" value-type="long" all="false" select-expr="sum(access_number17)" length="19" nullable="false" />
   		<member name="access-number-sum18" value-type="long" all="false" select-expr="sum(access_number18)" length="19" nullable="false" />
   		<member name="access-number-sum19" value-type="long" all="false" select-expr="sum(access_number19)" length="19" nullable="false" />
   		<member name="access-number-sum20" value-type="long" all="false" select-expr="sum(access_number20)" length="19" nullable="false" />
   		<member name="access-number-sum21" value-type="long" all="false" select-expr="sum(access_number21)" length="19" nullable="false" />
   		<member name="access-number-sum22" value-type="long" all="false" select-expr="sum(access_number22)" length="19" nullable="false" />
   		<member name="access-number-sum23" value-type="long" all="false" select-expr="sum(access_number23)" length="19" nullable="false" />
   		<member name="access-number-sum24" value-type="long" all="false" select-expr="sum(access_number24)" length="19" nullable="false" />
   		<member name="access-number-sum25" value-type="long" all="false" select-expr="sum(access_number25)" length="19" nullable="false" />
   		<member name="access-number-sum26" value-type="long" all="false" select-expr="sum(access_number26)" length="19" nullable="false" />
   		<member name="access-number-sum27" value-type="long" all="false" select-expr="sum(access_number27)" length="19" nullable="false" />
   		<member name="access-number-sum28" value-type="long" all="false" select-expr="sum(access_number28)" length="19" nullable="false" />
   		<member name="access-number-sum29" value-type="long" all="false" select-expr="sum(access_number29)" length="19" nullable="false" />
   		<member name="access-number-sum30" value-type="long" all="false" select-expr="sum(access_number30)" length="19" nullable="false" />
   		<member name="access-number-sum31" value-type="long" all="false" select-expr="sum(access_number31)" length="19" nullable="false" />
   		<member name="access-number-sum32" value-type="long" all="false" select-expr="sum(access_number32)" length="19" nullable="false" />
  		<member name="response-sum-time-sum1" value-type="long" all="false" select-expr="sum(response_sum_time1)" length="19" nullable="false" />
  		<member name="response-sum-time-sum2" value-type="long" all="false" select-expr="sum(response_sum_time2)" length="19" nullable="false" />
  		<member name="response-sum-time-sum3" value-type="long" all="false" select-expr="sum(response_sum_time3)" length="19" nullable="false" />
  		<member name="response-sum-time-sum4" value-type="long" all="false" select-expr="sum(response_sum_time4)" length="19" nullable="false" />
  		<member name="response-sum-time-sum5" value-type="long" all="false" select-expr="sum(response_sum_time5)" length="19" nullable="false" />
  		<member name="response-sum-time-sum6" value-type="long" all="false" select-expr="sum(response_sum_time6)" length="19" nullable="false" />
  		<member name="response-sum-time-sum7" value-type="long" all="false" select-expr="sum(response_sum_time7)" length="19" nullable="false" />
  		<member name="response-sum-time-sum8" value-type="long" all="false" select-expr="sum(response_sum_time8)" length="19" nullable="false" />
  		<member name="response-sum-time-sum9" value-type="long" all="false" select-expr="sum(response_sum_time9)" length="19" nullable="false" />
  		<member name="response-sum-time-sum10" value-type="long" all="false" select-expr="sum(response_sum_time10)" length="19" nullable="false" />
  		<member name="response-sum-time-sum11" value-type="long" all="false" select-expr="sum(response_sum_time11)" length="19" nullable="false" />
  		<member name="response-sum-time-sum12" value-type="long" all="false" select-expr="sum(response_sum_time12)" length="19" nullable="false" />
  		<member name="response-sum-time-sum13" value-type="long" all="false" select-expr="sum(response_sum_time13)" length="19" nullable="false" />
  		<member name="response-sum-time-sum14" value-type="long" all="false" select-expr="sum(response_sum_time14)" length="19" nullable="false" />
  		<member name="response-sum-time-sum15" value-type="long" all="false" select-expr="sum(response_sum_time15)" length="19" nullable="false" />
  		<member name="response-sum-time-sum16" value-type="long" all="false" select-expr="sum(response_sum_time16)" length="19" nullable="false" />
  		<member name="response-sum-time-sum17" value-type="long" all="false" select-expr="sum(response_sum_time17)" length="19" nullable="false" />
  		<member name="response-sum-time-sum18" value-type="long" all="false" select-expr="sum(response_sum_time18)" length="19" nullable="false" />
  		<member name="response-sum-time-sum19" value-type="long" all="false" select-expr="sum(response_sum_time19)" length="19" nullable="false" />
  		<member name="response-sum-time-sum20" value-type="long" all="false" select-expr="sum(response_sum_time20)" length="19" nullable="false" />
  		<member name="response-sum-time-sum21" value-type="long" all="false" select-expr="sum(response_sum_time21)" length="19" nullable="false" />
  		<member name="response-sum-time-sum22" value-type="long" all="false" select-expr="sum(response_sum_time22)" length="19" nullable="false" />
  		<member name="response-sum-time-sum23" value-type="long" all="false" select-expr="sum(response_sum_time23)" length="19" nullable="false" />
  		<member name="response-sum-time-sum24" value-type="long" all="false" select-expr="sum(response_sum_time24)" length="19" nullable="false" />
  		<member name="response-sum-time-sum25" value-type="long" all="false" select-expr="sum(response_sum_time25)" length="19" nullable="false" />
  		<member name="response-sum-time-sum26" value-type="long" all="false" select-expr="sum(response_sum_time26)" length="19" nullable="false" />
  		<member name="response-sum-time-sum27" value-type="long" all="false" select-expr="sum(response_sum_time27)" length="19" nullable="false" />
  		<member name="response-sum-time-sum28" value-type="long" all="false" select-expr="sum(response_sum_time28)" length="19" nullable="false" />
  		<member name="response-sum-time-sum29" value-type="long" all="false" select-expr="sum(response_sum_time29)" length="19" nullable="false" />
  		<member name="response-sum-time-sum30" value-type="long" all="false" select-expr="sum(response_sum_time30)" length="19" nullable="false" />
  		<member name="response-sum-time-sum31" value-type="long" all="false" select-expr="sum(response_sum_time31)" length="19" nullable="false" />
  		<member name="response-sum-time-sum32" value-type="long" all="false" select-expr="sum(response_sum_time32)" length="19" nullable="false" />
		<member name="response-sum-time-sum" value-type="long" length="19"/>
		<member name="access-number-sum" value-type="long" length="19"/>
		<member name="response-sum-time-sum" value-type="long" length="19"/>
		
		<var name="start-minute-order" value-type="int" />
		<var name="end-minute-order" value-type="int" />
		<var name="speed-id" value-type="int" />
		
		<readsets>
		<readset name="AVG-DATA1">
      		<member name="minute-order"/>
      		<member name="access-number-sum1"/>
      		<member name="response-sum-time-sum1"/>
      	</readset>
      	<readset name="AVG-DATA2">
      		<member name="minute-order"/>
      		<member name="access-number-sum2"/>
      		<member name="response-sum-time-sum2"/>
      	</readset>
      	<readset name="AVG-DATA3">
      		<member name="minute-order"/>
      		<member name="access-number-sum3"/>
      		<member name="response-sum-time-sum3"/>
      	</readset>
      	<readset name="AVG-DATA4">
      		<member name="minute-order"/>
      		<member name="access-number-sum4"/>
      		<member name="response-sum-time-sum4"/>
      	</readset>
      	<readset name="AVG-DATA5">
      		<member name="minute-order"/>
      		<member name="access-number-sum5"/>
      		<member name="response-sum-time-sum5"/>
      	</readset>
      	<readset name="AVG-DATA6">
      		<member name="minute-order"/>
      		<member name="access-number-sum6"/>
      		<member name="response-sum-time-sum6"/>
      	</readset>
      	<readset name="AVG-DATA7">
      		<member name="minute-order"/>
      		<member name="access-number-sum7"/>
      		<member name="response-sum-time-sum7"/>
      	</readset>
      	<readset name="AVG-DATA8">
      		<member name="minute-order"/>
      		<member name="access-number-sum8"/>
      		<member name="response-sum-time-sum8"/>
      	</readset>
      	<readset name="AVG-DATA9">
      		<member name="minute-order"/>
      		<member name="access-number-sum9"/>
      		<member name="response-sum-time-sum9"/>
      	</readset>
      	<readset name="AVG-DATA10">
      		<member name="minute-order"/>
      		<member name="access-number-sum10"/>
      		<member name="response-sum-time-sum10"/>
      	</readset>
      	<readset name="AVG-DATA11">
      		<member name="minute-order"/>
      		<member name="access-number-sum11"/>
      		<member name="response-sum-time-sum11"/>
      	</readset>
      	<readset name="AVG-DATA12">
      		<member name="minute-order"/>
      		<member name="access-number-sum12"/>
      		<member name="response-sum-time-sum12"/>
      	</readset>
      	<readset name="AVG-DATA13">
      		<member name="minute-order"/>
      		<member name="access-number-sum13"/>
      		<member name="response-sum-time-sum13"/>
      	</readset>
      	<readset name="AVG-DATA14">
      		<member name="minute-order"/>
      		<member name="access-number-sum14"/>
      		<member name="response-sum-time-sum14"/>
      	</readset>
      	<readset name="AVG-DATA15">
      		<member name="minute-order"/>
      		<member name="access-number-sum15"/>
      		<member name="response-sum-time-sum15"/>
      	</readset>
      	<readset name="AVG-DATA16">
      		<member name="minute-order"/>
      		<member name="access-number-sum16"/>
      		<member name="response-sum-time-sum16"/>
      	</readset>
      	<readset name="AVG-DATA17">
      		<member name="minute-order"/>
      		<member name="access-number-sum17"/>
      		<member name="response-sum-time-sum17"/>
      	</readset>
      	<readset name="AVG-DATA18">
      		<member name="minute-order"/>
      		<member name="access-number-sum18"/>
      		<member name="response-sum-time-sum18"/>
      	</readset>
      	<readset name="AVG-DATA19">
      		<member name="minute-order"/>
      		<member name="access-number-sum19"/>
      		<member name="response-sum-time-sum19"/>
      	</readset>
      	<readset name="AVG-DATA20">
      		<member name="minute-order"/>
      		<member name="access-number-sum20"/>
      		<member name="response-sum-time-sum20"/>
      	</readset>
      	<readset name="AVG-DATA21">
      		<member name="minute-order"/>
      		<member name="access-number-sum21"/>
      		<member name="response-sum-time-sum21"/>
      	</readset>
      	<readset name="AVG-DATA22">
      		<member name="minute-order"/>
      		<member name="access-number-sum22"/>
      		<member name="response-sum-time-sum22"/>
      	</readset>
      	<readset name="AVG-DATA23">
      		<member name="minute-order"/>
      		<member name="access-number-sum23"/>
      		<member name="response-sum-time-sum23"/>
      	</readset>
      	<readset name="AVG-DATA24">
      		<member name="minute-order"/>
      		<member name="access-number-sum24"/>
      		<member name="response-sum-time-sum24"/>
      	</readset>
      	<readset name="AVG-DATA25">
      		<member name="minute-order"/>
      		<member name="access-number-sum25"/>
      		<member name="response-sum-time-sum25"/>
      	</readset>
      	<readset name="AVG-DATA26">
      		<member name="minute-order"/>
      		<member name="access-number-sum26"/>
      		<member name="response-sum-time-sum26"/>
      	</readset>
      	<readset name="AVG-DATA27">
      		<member name="minute-order"/>
      		<member name="access-number-sum27"/>
      		<member name="response-sum-time-sum27"/>
      	</readset>
      	<readset name="AVG-DATA28">
      		<member name="minute-order"/>
      		<member name="access-number-sum28"/>
      		<member name="response-sum-time-sum28"/>
      	</readset>
      	<readset name="AVG-DATA29">
      		<member name="minute-order"/>
      		<member name="access-number-sum29"/>
      		<member name="response-sum-time-sum29"/>
      	</readset>
      	<readset name="AVG-DATA30">
      		<member name="minute-order"/>
      		<member name="access-number-sum30"/>
      		<member name="response-sum-time-sum30"/>
      	</readset>
      	<readset name="AVG-DATA31">
      		<member name="minute-order"/>
      		<member name="access-number-sum31"/>
      		<member name="response-sum-time-sum31"/>
      	</readset>
      	<readset name="AVG-DATA32">
      		<member name="minute-order"/>
      		<member name="access-number-sum32"/>
      		<member name="response-sum-time-sum32"/>
      	</readset>
      	<readset name="CITY-DATA1">
      		<member name="city"/>
      		<member name="access-number-sum1"/>
      		<member name="response-sum-time-sum1"/>
      	</readset>
      	<readset name="CITY-DATA2">
      		<member name="city"/>
      		<member name="access-number-sum2"/>
      		<member name="response-sum-time-sum2"/>
      	</readset>
      	<readset name="CITY-DATA3">
      		<member name="city"/>
      		<member name="access-number-sum3"/>
      		<member name="response-sum-time-sum3"/>
      	</readset>
      	<readset name="CITY-DATA4">
      		<member name="city"/>
      		<member name="access-number-sum4"/>
      		<member name="response-sum-time-sum4"/>
      	</readset>
      	<readset name="CITY-DATA5">
      		<member name="city"/>
      		<member name="access-number-sum5"/>
      		<member name="response-sum-time-sum5"/>
      	</readset>
      	<readset name="CITY-DATA6">
      		<member name="city"/>
      		<member name="access-number-sum6"/>
      		<member name="response-sum-time-sum6"/>
      	</readset>
      	<readset name="CITY-DATA7">
      		<member name="city"/>
      		<member name="access-number-sum7"/>
      		<member name="response-sum-time-sum7"/>
      	</readset>
      	<readset name="CITY-DATA8">
      		<member name="city"/>
      		<member name="access-number-sum8"/>
      		<member name="response-sum-time-sum8"/>
      	</readset>
      	<readset name="CITY-DATA9">
      		<member name="city"/>
      		<member name="access-number-sum9"/>
      		<member name="response-sum-time-sum9"/>
      	</readset>
      	<readset name="CITY-DATA10">
      		<member name="city"/>
      		<member name="access-number-sum10"/>
      		<member name="response-sum-time-sum10"/>
      	</readset>
      	<readset name="CITY-DATA11">
      		<member name="city"/>
      		<member name="access-number-sum11"/>
      		<member name="response-sum-time-sum11"/>
      	</readset>
      	<readset name="CITY-DATA12">
      		<member name="city"/>
      		<member name="access-number-sum12"/>
      		<member name="response-sum-time-sum12"/>
      	</readset>
      	<readset name="CITY-DATA13">
      		<member name="city"/>
      		<member name="access-number-sum13"/>
      		<member name="response-sum-time-sum13"/>
      	</readset>
      	<readset name="CITY-DATA14">
      		<member name="city"/>
      		<member name="access-number-sum14"/>
      		<member name="response-sum-time-sum14"/>
      	</readset>
      	<readset name="CITY-DATA15">
      		<member name="city"/>
      		<member name="access-number-sum15"/>
      		<member name="response-sum-time-sum15"/>
      	</readset>
      	<readset name="CITY-DATA16">
      		<member name="city"/>
      		<member name="access-number-sum16"/>
      		<member name="response-sum-time-sum16"/>
      	</readset>
      	<readset name="CITY-DATA17">
      		<member name="city"/>
      		<member name="access-number-sum17"/>
      		<member name="response-sum-time-sum17"/>
      	</readset>
      	<readset name="CITY-DATA18">
      		<member name="city"/>
      		<member name="access-number-sum18"/>
      		<member name="response-sum-time-sum18"/>
      	</readset>
      	<readset name="CITY-DATA19">
      		<member name="city"/>
      		<member name="access-number-sum19"/>
      		<member name="response-sum-time-sum19"/>
      	</readset>
      	<readset name="CITY-DATA20">
      		<member name="city"/>
      		<member name="access-number-sum20"/>
      		<member name="response-sum-time-sum20"/>
      	</readset>
      	<readset name="CITY-DATA21">
      		<member name="city"/>
      		<member name="access-number-sum21"/>
      		<member name="response-sum-time-sum21"/>
      	</readset>
      	<readset name="CITY-DATA22">
      		<member name="city"/>
      		<member name="access-number-sum22"/>
      		<member name="response-sum-time-sum22"/>
      	</readset>
      	<readset name="CITY-DATA23">
      		<member name="city"/>
      		<member name="access-number-sum23"/>
      		<member name="response-sum-time-sum23"/>
      	</readset>
      	<readset name="CITY-DATA24">
      		<member name="city"/>
      		<member name="access-number-sum24"/>
      		<member name="response-sum-time-sum24"/>
      	</readset>
      	<readset name="CITY-DATA25">
      		<member name="city"/>
      		<member name="access-number-sum25"/>
      		<member name="response-sum-time-sum25"/>
      	</readset>
      	<readset name="CITY-DATA26">
      		<member name="city"/>
      		<member name="access-number-sum26"/>
      		<member name="response-sum-time-sum26"/>
      	</readset>
      	<readset name="CITY-DATA27">
      		<member name="city"/>
      		<member name="access-number-sum27"/>
      		<member name="response-sum-time-sum27"/>
      	</readset>
      	<readset name="CITY-DATA28">
      		<member name="city"/>
      		<member name="access-number-sum28"/>
      		<member name="response-sum-time-sum28"/>
      	</readset>
      	<readset name="CITY-DATA29">
      		<member name="city"/>
      		<member name="access-number-sum29"/>
      		<member name="response-sum-time-sum29"/>
      	</readset>
      	<readset name="CITY-DATA30">
      		<member name="city"/>
      		<member name="access-number-sum30"/>
      		<member name="response-sum-time-sum30"/>
      	</readset>
      	<readset name="CITY-DATA31">
      		<member name="city"/>
      		<member name="access-number-sum31"/>
      		<member name="response-sum-time-sum31"/>
      	</readset>
      	<readset name="CITY-DATA32">
      		<member name="city"/>
      		<member name="access-number-sum32"/>
      		<member name="response-sum-time-sum32"/>
      	</readset>
      		<readset name="PLATFORM-DATA1">
      		<member name="platform"/>
      		<member name="access-number-sum1"/>
      		<member name="response-sum-time-sum1"/>
      	</readset>
      	<readset name="PLATFORM-DATA2">
      		<member name="platform"/>
      		<member name="access-number-sum2"/>
      		<member name="response-sum-time-sum2"/>
      	</readset>
      	<readset name="PLATFORM-DATA3">
      		<member name="platform"/>
      		<member name="access-number-sum3"/>
      		<member name="response-sum-time-sum3"/>
      	</readset>
      	<readset name="PLATFORM-DATA4">
      		<member name="platform"/>
      		<member name="access-number-sum4"/>
      		<member name="response-sum-time-sum4"/>
      	</readset>
      	<readset name="PLATFORM-DATA5">
      		<member name="platform"/>
      		<member name="access-number-sum5"/>
      		<member name="response-sum-time-sum5"/>
      	</readset>
      	<readset name="PLATFORM-DATA6">
      		<member name="platform"/>
      		<member name="access-number-sum6"/>
      		<member name="response-sum-time-sum6"/>
      	</readset>
      	<readset name="PLATFORM-DATA7">
      		<member name="platform"/>
      		<member name="access-number-sum7"/>
      		<member name="response-sum-time-sum7"/>
      	</readset>
      	<readset name="PLATFORM-DATA8">
      		<member name="platform"/>
      		<member name="access-number-sum8"/>
      		<member name="response-sum-time-sum8"/>
      	</readset>
      	<readset name="PLATFORM-DATA9">
      		<member name="platform"/>
      		<member name="access-number-sum9"/>
      		<member name="response-sum-time-sum9"/>
      	</readset>
      	<readset name="PLATFORM-DATA10">
      		<member name="platform"/>
      		<member name="access-number-sum10"/>
      		<member name="response-sum-time-sum10"/>
      	</readset>
      	<readset name="PLATFORM-DATA11">
      		<member name="platform"/>
      		<member name="access-number-sum11"/>
      		<member name="response-sum-time-sum11"/>
      	</readset>
      	<readset name="PLATFORM-DATA12">
      		<member name="platform"/>
      		<member name="access-number-sum12"/>
      		<member name="response-sum-time-sum12"/>
      	</readset>
      	<readset name="PLATFORM-DATA13">
      		<member name="platform"/>
      		<member name="access-number-sum13"/>
      		<member name="response-sum-time-sum13"/>
      	</readset>
      	<readset name="PLATFORM-DATA14">
      		<member name="platform"/>
      		<member name="access-number-sum14"/>
      		<member name="response-sum-time-sum14"/>
      	</readset>
      	<readset name="PLATFORM-DATA15">
      		<member name="platform"/>
      		<member name="access-number-sum15"/>
      		<member name="response-sum-time-sum15"/>
      	</readset>
      	<readset name="PLATFORM-DATA16">
      		<member name="platform"/>
      		<member name="access-number-sum16"/>
      		<member name="response-sum-time-sum16"/>
      	</readset>
      	<readset name="PLATFORM-DATA17">
      		<member name="platform"/>
      		<member name="access-number-sum17"/>
      		<member name="response-sum-time-sum17"/>
      	</readset>
      	<readset name="PLATFORM-DATA18">
      		<member name="platform"/>
      		<member name="access-number-sum18"/>
      		<member name="response-sum-time-sum18"/>
      	</readset>
      	<readset name="PLATFORM-DATA19">
      		<member name="platform"/>
      		<member name="access-number-sum19"/>
      		<member name="response-sum-time-sum19"/>
      	</readset>
      	<readset name="PLATFORM-DATA20">
      		<member name="platform"/>
      		<member name="access-number-sum20"/>
      		<member name="response-sum-time-sum20"/>
      	</readset>
      	<readset name="PLATFORM-DATA21">
      		<member name="platform"/>
      		<member name="access-number-sum21"/>
      		<member name="response-sum-time-sum21"/>
      	</readset>
      	<readset name="PLATFORM-DATA22">
      		<member name="platform"/>
      		<member name="access-number-sum22"/>
      		<member name="response-sum-time-sum22"/>
      	</readset>
      	<readset name="PLATFORM-DATA23">
      		<member name="platform"/>
      		<member name="access-number-sum23"/>
      		<member name="response-sum-time-sum23"/>
      	</readset>
      	<readset name="PLATFORM-DATA24">
      		<member name="platform"/>
      		<member name="access-number-sum24"/>
      		<member name="response-sum-time-sum24"/>
      	</readset>
      	<readset name="PLATFORM-DATA25">
      		<member name="platform"/>
      		<member name="access-number-sum25"/>
      		<member name="response-sum-time-sum25"/>
      	</readset>
      	<readset name="PLATFORM-DATA26">
      		<member name="platform"/>
      		<member name="access-number-sum26"/>
      		<member name="response-sum-time-sum26"/>
      	</readset>
      	<readset name="PLATFORM-DATA27">
      		<member name="platform"/>
      		<member name="access-number-sum27"/>
      		<member name="response-sum-time-sum27"/>
      	</readset>
      	<readset name="PLATFORM-DATA28">
      		<member name="platform"/>
      		<member name="access-number-sum28"/>
      		<member name="response-sum-time-sum28"/>
      	</readset>
      	<readset name="PLATFORM-DATA29">
      		<member name="platform"/>
      		<member name="access-number-sum29"/>
      		<member name="response-sum-time-sum29"/>
      	</readset>
      	<readset name="PLATFORM-DATA30">
      		<member name="platform"/>
      		<member name="access-number-sum30"/>
      		<member name="response-sum-time-sum30"/>
      	</readset>
      	<readset name="PLATFORM-DATA31">
      		<member name="platform"/>
      		<member name="access-number-sum31"/>
      		<member name="response-sum-time-sum31"/>
      	</readset>
      	<readset name="PLATFORM-DATA32">
      		<member name="platform"/>
      		<member name="access-number-sum32"/>
      		<member name="response-sum-time-sum32"/>
      	</readset>
      		<readset name="SOURCE-DATA1">
      		<member name="source"/>
      		<member name="access-number-sum1"/>
      		<member name="response-sum-time-sum1"/>
      	</readset>
      	<readset name="SOURCE-DATA2">
      		<member name="source"/>
      		<member name="access-number-sum2"/>
      		<member name="response-sum-time-sum2"/>
      	</readset>
      	<readset name="SOURCE-DATA3">
      		<member name="source"/>
      		<member name="access-number-sum3"/>
      		<member name="response-sum-time-sum3"/>
      	</readset>
      	<readset name="SOURCE-DATA4">
      		<member name="source"/>
      		<member name="access-number-sum4"/>
      		<member name="response-sum-time-sum4"/>
      	</readset>
      	<readset name="SOURCE-DATA5">
      		<member name="source"/>
      		<member name="access-number-sum5"/>
      		<member name="response-sum-time-sum5"/>
      	</readset>
      	<readset name="SOURCE-DATA6">
      		<member name="source"/>
      		<member name="access-number-sum6"/>
      		<member name="response-sum-time-sum6"/>
      	</readset>
      	<readset name="SOURCE-DATA7">
      		<member name="source"/>
      		<member name="access-number-sum7"/>
      		<member name="response-sum-time-sum7"/>
      	</readset>
      	<readset name="SOURCE-DATA8">
      		<member name="source"/>
      		<member name="access-number-sum8"/>
      		<member name="response-sum-time-sum8"/>
      	</readset>
      	<readset name="SOURCE-DATA9">
      		<member name="source"/>
      		<member name="access-number-sum9"/>
      		<member name="response-sum-time-sum9"/>
      	</readset>
      	<readset name="SOURCE-DATA10">
      		<member name="source"/>
      		<member name="access-number-sum10"/>
      		<member name="response-sum-time-sum10"/>
      	</readset>
      	<readset name="SOURCE-DATA11">
      		<member name="source"/>
      		<member name="access-number-sum11"/>
      		<member name="response-sum-time-sum11"/>
      	</readset>
      	<readset name="SOURCE-DATA12">
      		<member name="source"/>
      		<member name="access-number-sum12"/>
      		<member name="response-sum-time-sum12"/>
      	</readset>
      	<readset name="SOURCE-DATA13">
      		<member name="source"/>
      		<member name="access-number-sum13"/>
      		<member name="response-sum-time-sum13"/>
      	</readset>
      	<readset name="SOURCE-DATA14">
      		<member name="source"/>
      		<member name="access-number-sum14"/>
      		<member name="response-sum-time-sum14"/>
      	</readset>
      	<readset name="SOURCE-DATA15">
      		<member name="source"/>
      		<member name="access-number-sum15"/>
      		<member name="response-sum-time-sum15"/>
      	</readset>
      	<readset name="SOURCE-DATA16">
      		<member name="source"/>
      		<member name="access-number-sum16"/>
      		<member name="response-sum-time-sum16"/>
      	</readset>
      	<readset name="SOURCE-DATA17">
      		<member name="source"/>
      		<member name="access-number-sum17"/>
      		<member name="response-sum-time-sum17"/>
      	</readset>
      	<readset name="SOURCE-DATA18">
      		<member name="source"/>
      		<member name="access-number-sum18"/>
      		<member name="response-sum-time-sum18"/>
      	</readset>
      	<readset name="SOURCE-DATA19">
      		<member name="source"/>
      		<member name="access-number-sum19"/>
      		<member name="response-sum-time-sum19"/>
      	</readset>
      	<readset name="SOURCE-DATA20">
      		<member name="source"/>
      		<member name="access-number-sum20"/>
      		<member name="response-sum-time-sum20"/>
      	</readset>
      	<readset name="SOURCE-DATA21">
      		<member name="source"/>
      		<member name="access-number-sum21"/>
      		<member name="response-sum-time-sum21"/>
      	</readset>
      	<readset name="SOURCE-DATA22">
      		<member name="source"/>
      		<member name="access-number-sum22"/>
      		<member name="response-sum-time-sum22"/>
      	</readset>
      	<readset name="SOURCE-DATA23">
      		<member name="source"/>
      		<member name="access-number-sum23"/>
      		<member name="response-sum-time-sum23"/>
      	</readset>
      	<readset name="SOURCE-DATA24">
      		<member name="source"/>
      		<member name="access-number-sum24"/>
      		<member name="response-sum-time-sum24"/>
      	</readset>
      	<readset name="SOURCE-DATA25">
      		<member name="source"/>
      		<member name="access-number-sum25"/>
      		<member name="response-sum-time-sum25"/>
      	</readset>
      	<readset name="SOURCE-DATA26">
      		<member name="source"/>
      		<member name="access-number-sum26"/>
      		<member name="response-sum-time-sum26"/>
      	</readset>
      	<readset name="SOURCE-DATA27">
      		<member name="source"/>
      		<member name="access-number-sum27"/>
      		<member name="response-sum-time-sum27"/>
      	</readset>
      	<readset name="SOURCE-DATA28">
      		<member name="source"/>
      		<member name="access-number-sum28"/>
      		<member name="response-sum-time-sum28"/>
      	</readset>
      	<readset name="SOURCE-DATA29">
      		<member name="source"/>
      		<member name="access-number-sum29"/>
      		<member name="response-sum-time-sum29"/>
      	</readset>
      	<readset name="SOURCE-DATA30">
      		<member name="source"/>
      		<member name="access-number-sum30"/>
      		<member name="response-sum-time-sum30"/>
      	</readset>
      	<readset name="SOURCE-DATA31">
      		<member name="source"/>
      		<member name="access-number-sum31"/>
      		<member name="response-sum-time-sum31"/>
      	</readset>
      	<readset name="SOURCE-DATA32">
      		<member name="source"/>
      		<member name="access-number-sum32"/>
      		<member name="response-sum-time-sum32"/>
      	</readset>
      		<readset name="OPERATOR-DATA1">
      		<member name="operator"/>
      		<member name="access-number-sum1"/>
      		<member name="response-sum-time-sum1"/>
      	</readset>
      	<readset name="OPERATOR-DATA2">
      		<member name="operator"/>
      		<member name="access-number-sum2"/>
      		<member name="response-sum-time-sum2"/>
      	</readset>
      	<readset name="OPERATOR-DATA3">
      		<member name="operator"/>
      		<member name="access-number-sum3"/>
      		<member name="response-sum-time-sum3"/>
      	</readset>
      	<readset name="OPERATOR-DATA4">
      		<member name="operator"/>
      		<member name="access-number-sum4"/>
      		<member name="response-sum-time-sum4"/>
      	</readset>
      	<readset name="OPERATOR-DATA5">
      		<member name="operator"/>
      		<member name="access-number-sum5"/>
      		<member name="response-sum-time-sum5"/>
      	</readset>
      	<readset name="OPERATOR-DATA6">
      		<member name="operator"/>
      		<member name="access-number-sum6"/>
      		<member name="response-sum-time-sum6"/>
      	</readset>
      	<readset name="OPERATOR-DATA7">
      		<member name="operator"/>
      		<member name="access-number-sum7"/>
      		<member name="response-sum-time-sum7"/>
      	</readset>
      	<readset name="OPERATOR-DATA8">
      		<member name="operator"/>
      		<member name="access-number-sum8"/>
      		<member name="response-sum-time-sum8"/>
      	</readset>
      	<readset name="OPERATOR-DATA9">
      		<member name="operator"/>
      		<member name="access-number-sum9"/>
      		<member name="response-sum-time-sum9"/>
      	</readset>
      	<readset name="OPERATOR-DATA10">
      		<member name="operator"/>
      		<member name="access-number-sum10"/>
      		<member name="response-sum-time-sum10"/>
      	</readset>
      	<readset name="OPERATOR-DATA11">
      		<member name="operator"/>
      		<member name="access-number-sum11"/>
      		<member name="response-sum-time-sum11"/>
      	</readset>
      	<readset name="OPERATOR-DATA12">
      		<member name="operator"/>
      		<member name="access-number-sum12"/>
      		<member name="response-sum-time-sum12"/>
      	</readset>
      	<readset name="OPERATOR-DATA13">
      		<member name="operator"/>
      		<member name="access-number-sum13"/>
      		<member name="response-sum-time-sum13"/>
      	</readset>
      	<readset name="OPERATOR-DATA14">
      		<member name="operator"/>
      		<member name="access-number-sum14"/>
      		<member name="response-sum-time-sum14"/>
      	</readset>
      	<readset name="OPERATOR-DATA15">
      		<member name="operator"/>
      		<member name="access-number-sum15"/>
      		<member name="response-sum-time-sum15"/>
      	</readset>
      	<readset name="OPERATOR-DATA16">
      		<member name="operator"/>
      		<member name="access-number-sum16"/>
      		<member name="response-sum-time-sum16"/>
      	</readset>
      	<readset name="OPERATOR-DATA17">
      		<member name="operator"/>
      		<member name="access-number-sum17"/>
      		<member name="response-sum-time-sum17"/>
      	</readset>
      	<readset name="OPERATOR-DATA18">
      		<member name="operator"/>
      		<member name="access-number-sum18"/>
      		<member name="response-sum-time-sum18"/>
      	</readset>
      	<readset name="OPERATOR-DATA19">
      		<member name="operator"/>
      		<member name="access-number-sum19"/>
      		<member name="response-sum-time-sum19"/>
      	</readset>
      	<readset name="OPERATOR-DATA20">
      		<member name="operator"/>
      		<member name="access-number-sum20"/>
      		<member name="response-sum-time-sum20"/>
      	</readset>
      	<readset name="OPERATOR-DATA21">
      		<member name="operator"/>
      		<member name="access-number-sum21"/>
      		<member name="response-sum-time-sum21"/>
      	</readset>
      	<readset name="OPERATOR-DATA22">
      		<member name="operator"/>
      		<member name="access-number-sum22"/>
      		<member name="response-sum-time-sum22"/>
      	</readset>
      	<readset name="OPERATOR-DATA23">
      		<member name="operator"/>
      		<member name="access-number-sum23"/>
      		<member name="response-sum-time-sum23"/>
      	</readset>
      	<readset name="OPERATOR-DATA24">
      		<member name="operator"/>
      		<member name="access-number-sum24"/>
      		<member name="response-sum-time-sum24"/>
      	</readset>
      	<readset name="OPERATOR-DATA25">
      		<member name="operator"/>
      		<member name="access-number-sum25"/>
      		<member name="response-sum-time-sum25"/>
      	</readset>
      	<readset name="OPERATOR-DATA26">
      		<member name="operator"/>
      		<member name="access-number-sum26"/>
      		<member name="response-sum-time-sum26"/>
      	</readset>
      	<readset name="OPERATOR-DATA27">
      		<member name="operator"/>
      		<member name="access-number-sum27"/>
      		<member name="response-sum-time-sum27"/>
      	</readset>
      	<readset name="OPERATOR-DATA28">
      		<member name="operator"/>
      		<member name="access-number-sum28"/>
      		<member name="response-sum-time-sum28"/>
      	</readset>
      	<readset name="OPERATOR-DATA29">
      		<member name="operator"/>
      		<member name="access-number-sum29"/>
      		<member name="response-sum-time-sum29"/>
      	</readset>
      	<readset name="OPERATOR-DATA30">
      		<member name="operator"/>
      		<member name="access-number-sum30"/>
      		<member name="response-sum-time-sum30"/>
      	</readset>
      	<readset name="OPERATOR-DATA31">
      		<member name="operator"/>
      		<member name="access-number-sum31"/>
      		<member name="response-sum-time-sum31"/>
      	</readset>
      	<readset name="OPERATOR-DATA32">
      		<member name="operator"/>
      		<member name="access-number-sum32"/>
      		<member name="response-sum-time-sum32"/>
      	</readset>
      	<readset name="NETWORK-DATA1">
      		<member name="network"/>
      		<member name="access-number-sum1"/>
      		<member name="response-sum-time-sum1"/>
      	</readset>
      	<readset name="NETWORK-DATA2">
      		<member name="network"/>
      		<member name="access-number-sum2"/>
      		<member name="response-sum-time-sum2"/>
      	</readset>
      	<readset name="NETWORK-DATA3">
      		<member name="network"/>
      		<member name="access-number-sum3"/>
      		<member name="response-sum-time-sum3"/>
      	</readset>
      	<readset name="NETWORK-DATA4">
      		<member name="network"/>
      		<member name="access-number-sum4"/>
      		<member name="response-sum-time-sum4"/>
      	</readset>
      	<readset name="NETWORK-DATA5">
      		<member name="network"/>
      		<member name="access-number-sum5"/>
      		<member name="response-sum-time-sum5"/>
      	</readset>
      	<readset name="NETWORK-DATA6">
      		<member name="network"/>
      		<member name="access-number-sum6"/>
      		<member name="response-sum-time-sum6"/>
      	</readset>
      	<readset name="NETWORK-DATA7">
      		<member name="network"/>
      		<member name="access-number-sum7"/>
      		<member name="response-sum-time-sum7"/>
      	</readset>
      	<readset name="NETWORK-DATA8">
      		<member name="network"/>
      		<member name="access-number-sum8"/>
      		<member name="response-sum-time-sum8"/>
      	</readset>
      	<readset name="NETWORK-DATA9">
      		<member name="network"/>
      		<member name="access-number-sum9"/>
      		<member name="response-sum-time-sum9"/>
      	</readset>
      	<readset name="NETWORK-DATA10">
      		<member name="network"/>
      		<member name="access-number-sum10"/>
      		<member name="response-sum-time-sum10"/>
      	</readset>
      	<readset name="NETWORK-DATA11">
      		<member name="network"/>
      		<member name="access-number-sum11"/>
      		<member name="response-sum-time-sum11"/>
      	</readset>
      	<readset name="NETWORK-DATA12">
      		<member name="network"/>
      		<member name="access-number-sum12"/>
      		<member name="response-sum-time-sum12"/>
      	</readset>
      	<readset name="NETWORK-DATA13">
      		<member name="network"/>
      		<member name="access-number-sum13"/>
      		<member name="response-sum-time-sum13"/>
      	</readset>
      	<readset name="NETWORK-DATA14">
      		<member name="network"/>
      		<member name="access-number-sum14"/>
      		<member name="response-sum-time-sum14"/>
      	</readset>
      	<readset name="NETWORK-DATA15">
      		<member name="network"/>
      		<member name="access-number-sum15"/>
      		<member name="response-sum-time-sum15"/>
      	</readset>
      	<readset name="NETWORK-DATA16">
      		<member name="network"/>
      		<member name="access-number-sum16"/>
      		<member name="response-sum-time-sum16"/>
      	</readset>
      	<readset name="NETWORK-DATA17">
      		<member name="network"/>
      		<member name="access-number-sum17"/>
      		<member name="response-sum-time-sum17"/>
      	</readset>
      	<readset name="NETWORK-DATA18">
      		<member name="network"/>
      		<member name="access-number-sum18"/>
      		<member name="response-sum-time-sum18"/>
      	</readset>
      	<readset name="NETWORK-DATA19">
      		<member name="network"/>
      		<member name="access-number-sum19"/>
      		<member name="response-sum-time-sum19"/>
      	</readset>
      	<readset name="NETWORK-DATA20">
      		<member name="network"/>
      		<member name="access-number-sum20"/>
      		<member name="response-sum-time-sum20"/>
      	</readset>
      	<readset name="NETWORK-DATA21">
      		<member name="network"/>
      		<member name="access-number-sum21"/>
      		<member name="response-sum-time-sum21"/>
      	</readset>
      	<readset name="NETWORK-DATA22">
      		<member name="network"/>
      		<member name="access-number-sum22"/>
      		<member name="response-sum-time-sum22"/>
      	</readset>
      	<readset name="NETWORK-DATA23">
      		<member name="network"/>
      		<member name="access-number-sum23"/>
      		<member name="response-sum-time-sum23"/>
      	</readset>
      	<readset name="NETWORK-DATA24">
      		<member name="network"/>
      		<member name="access-number-sum24"/>
      		<member name="response-sum-time-sum24"/>
      	</readset>
      	<readset name="NETWORK-DATA25">
      		<member name="network"/>
      		<member name="access-number-sum25"/>
      		<member name="response-sum-time-sum25"/>
      	</readset>
      	<readset name="NETWORK-DATA26">
      		<member name="network"/>
      		<member name="access-number-sum26"/>
      		<member name="response-sum-time-sum26"/>
      	</readset>
      	<readset name="NETWORK-DATA27">
      		<member name="network"/>
      		<member name="access-number-sum27"/>
      		<member name="response-sum-time-sum27"/>
      	</readset>
      	<readset name="NETWORK-DATA28">
      		<member name="network"/>
      		<member name="access-number-sum28"/>
      		<member name="response-sum-time-sum28"/>
      	</readset>
      	<readset name="NETWORK-DATA29">
      		<member name="network"/>
      		<member name="access-number-sum29"/>
      		<member name="response-sum-time-sum29"/>
      	</readset>
      	<readset name="NETWORK-DATA30">
      		<member name="network"/>
      		<member name="access-number-sum30"/>
      		<member name="response-sum-time-sum30"/>
      	</readset>
      	<readset name="NETWORK-DATA31">
      		<member name="network"/>
      		<member name="access-number-sum31"/>
      		<member name="response-sum-time-sum31"/>
      	</readset>
      	<readset name="NETWORK-DATA32">
      		<member name="network"/>
      		<member name="access-number-sum32"/>
      		<member name="response-sum-time-sum32"/>
      	</readset>
		</readsets>
		<query-defs>
		<query name="insert" type="INSERT" batch="true">
			<statement><![CDATA[INSERT INTO <TABLE/>(<FIELDS/>)
        VALUES(<VALUES/>)]]></statement>
		</query>
		<query name="insert-or-update" type="INSERT"  batch="true">
        <statement><![CDATA[INSERT INTO <TABLE/>(<FIELDS/>)
        VALUES(<VALUES/>) ON DUPLICATE KEY UPDATE 
        access_number1 = access_number1 + ${access-number1},
        access_number2 = access_number2 + ${access-number2},
        access_number3 = access_number3 + ${access-number3},
        access_number4 = access_number4 + ${access-number4},
        access_number5 = access_number5 + ${access-number5},
        access_number6 = access_number6 + ${access-number6},
        access_number7 = access_number7 + ${access-number7},
        access_number8 = access_number8 + ${access-number8},
        access_number9 = access_number9 + ${access-number9},
        access_number10 = access_number10 + ${access-number10},
        access_number11 = access_number11 + ${access-number11},
        access_number12 = access_number12 + ${access-number12},
        access_number13 = access_number13 + ${access-number13},
        access_number14 = access_number14 + ${access-number14},
        access_number15 = access_number15 + ${access-number15},
        access_number16 = access_number16 + ${access-number16},
        access_number17 = access_number17 + ${access-number17},
        access_number18 = access_number18 + ${access-number18},
        access_number19 = access_number19 + ${access-number19},
        access_number20 = access_number20 + ${access-number20},
        access_number21 = access_number21 + ${access-number21},
        access_number22 = access_number22 + ${access-number22},
        access_number23 = access_number23 + ${access-number23},
        access_number24 = access_number24 + ${access-number24},
        access_number25 = access_number25 + ${access-number25},
        access_number26 = access_number26 + ${access-number26},
        access_number27 = access_number27 + ${access-number27},
        access_number28 = access_number28 + ${access-number28},
        access_number29 = access_number29 + ${access-number29},
        access_number30 = access_number30 + ${access-number30},
        access_number31 = access_number31 + ${access-number31},
        access_number32 = access_number32 + ${access-number32},
        response_sum_time1 = response_sum_time1 + ${response-sum-time1},
        response_sum_time2 = response_sum_time2 + ${response-sum-time2},
        response_sum_time3 = response_sum_time3 + ${response-sum-time3},
        response_sum_time4 = response_sum_time4 + ${response-sum-time4},
        response_sum_time5 = response_sum_time5 + ${response-sum-time5},
        response_sum_time6 = response_sum_time6 + ${response-sum-time6},
        response_sum_time7 = response_sum_time7 + ${response-sum-time7},
        response_sum_time8 = response_sum_time8 + ${response-sum-time8},
        response_sum_time9 = response_sum_time9 + ${response-sum-time9},
        response_sum_time10 = response_sum_time10 + ${response-sum-time10},
        response_sum_time11 = response_sum_time11 + ${response-sum-time11},
        response_sum_time12 = response_sum_time12 + ${response-sum-time12},
        response_sum_time13 = response_sum_time13 + ${response-sum-time13},
        response_sum_time14 = response_sum_time14 + ${response-sum-time14},
        response_sum_time15 = response_sum_time15 + ${response-sum-time15},
        response_sum_time16 = response_sum_time16 + ${response-sum-time16},
        response_sum_time17 = response_sum_time17 + ${response-sum-time17},
        response_sum_time18 = response_sum_time18 + ${response-sum-time18},
        response_sum_time19 = response_sum_time19 + ${response-sum-time19},
        response_sum_time20 = response_sum_time20 + ${response-sum-time20},
        response_sum_time21 = response_sum_time21 + ${response-sum-time21},
        response_sum_time22 = response_sum_time22 + ${response-sum-time22},
        response_sum_time23 = response_sum_time23 + ${response-sum-time23},
        response_sum_time24 = response_sum_time24 + ${response-sum-time24},
        response_sum_time25 = response_sum_time25 + ${response-sum-time25},
        response_sum_time26 = response_sum_time26 + ${response-sum-time26},
        response_sum_time27 = response_sum_time27 + ${response-sum-time27},
        response_sum_time28 = response_sum_time28 + ${response-sum-time28},
        response_sum_time29 = response_sum_time29 + ${response-sum-time29},
        response_sum_time30 = response_sum_time30 + ${response-sum-time30},
        response_sum_time31 = response_sum_time31 + ${response-sum-time31},
        response_sum_time32 = response_sum_time32 + ${response-sum-time32}
         ]]></statement>
      </query>  
       <query name="delete-before-period" type="DELETE">
        <param name="period" />
        <statement><![CDATA[DELETE FROM <TABLE/>
        WHERE <FIELD name='period'/> <= ${period}]]></statement>
      </query>  
      <query name="find-data-by-minute" type="SELECT" multiple="true">
        <param name="speed-id" />
        <param name="period" />
        <param name="city" />
        <param name="operator" />
        <param name="network" />
        <param name="platform" />
        <param name="source" />
        <statement><![CDATA[SELECT <FIELDS/>
        FROM <TABLE/>
        WHERE <FIELD name='period'/> = ${period} 
        <IF type='NE' field='city' value='-1'>
			AND  <FIELD name='city'/> = ${city}
		</IF>
        <IF type='NE' field='operator' value='-1'>
			AND  <FIELD name='operator'/> = ${operator}
		</IF>
        <IF type='NE' field='network' value='-1'>
			AND  <FIELD name='network'/> = ${network}
		</IF>
		<IF type='NE' field='platform' value='-1'>
			AND  <FIELD name='platform'/> = ${platform}
		</IF>
		<IF type='NE' field='source' value='-1'>
			AND  <FIELD name='source'/> = ${source}
		</IF>
        group by  <FIELD name='minute-order'/>  ]]></statement>
      </query>
      <query name="find-data-by-city" type="SELECT" multiple="true">
        <param name="speed-id" />
        <param name="period" />
        <param name="city" />
        <param name="operator" />
        <param name="network" />
        <param name="platform" />
        <param name="source" />
        <param name="start-minute-order" />
        <param name="end-minute-order" />
        <statement><![CDATA[SELECT <FIELDS/>
        FROM <TABLE/>
        WHERE <FIELD name='period'/> = ${period} 
        <IF type='NE' field='start-minute-order' value='-1'>
			AND  <FIELD name='minute-order'/> >= ${start-minute-order}
		</IF>
		<IF type='NE' field='end-minute-order' value='-1'>
			AND  <FIELD name='minute-order'/> <= ${end-minute-order}
		</IF> 
        <IF type='NE' field='city' value='-1'>
			AND  <FIELD name='city'/> = ${city}
		</IF>
        <IF type='NE' field='operator' value='-1'>
			AND  <FIELD name='operator'/> = ${operator}
		</IF>
        <IF type='NE' field='network' value='-1'>
			AND  <FIELD name='network'/> = ${network}
		</IF>
		<IF type='NE' field='platform' value='-1'>
			AND  <FIELD name='platform'/> = ${platform}
		</IF>
		<IF type='NE' field='source' value='-1'>
			AND  <FIELD name='source'/> = ${source}
		</IF>
        group by  <FIELD name='city'/>  ]]></statement>
      </query>
      <query name="find-data-by-platform" type="SELECT" multiple="true">
        <param name="speed-id" />
        <param name="period" />
        <param name="city" />
        <param name="operator" />
        <param name="network" />
        <param name="platform" />
        <param name="source" />
        <param name="start-minute-order" />
        <param name="end-minute-order" />
        <statement><![CDATA[SELECT <FIELDS/>
        FROM <TABLE/>
        WHERE <FIELD name='period'/> = ${period} 
        <IF type='NE' field='city' value='-1'>
			AND  <FIELD name='city'/> = ${city}
		</IF>
		<IF type='NE' field='start-minute-order' value='-1'>
			AND  <FIELD name='minute-order'/> >= ${start-minute-order}
		</IF>
		<IF type='NE' field='end-minute-order' value='-1'>
			AND  <FIELD name='minute-order'/> <= ${end-minute-order}
		</IF> 
        <IF type='NE' field='operator' value='-1'>
			AND  <FIELD name='operator'/> = ${operator}
		</IF>
        <IF type='NE' field='network' value='-1'>
			AND  <FIELD name='network'/> = ${network}
		</IF>
		<IF type='NE' field='platform' value='-1'>
			AND  <FIELD name='platform'/> = ${platform}
		</IF>
		<IF type='NE' field='source' value='-1'>
			AND  <FIELD name='source'/> = ${source}
		</IF>
        group by  <FIELD name='platform'/>  ]]></statement>
      </query>
       <query name="find-data-by-operator" type="SELECT" multiple="true">
        <param name="speed-id" />
        <param name="period" />
        <param name="city" />
        <param name="operator" />
        <param name="network" />
        <param name="platform" />
        <param name="source" />
        <param name="start-minute-order" />
        <param name="end-minute-order" />
        <statement><![CDATA[SELECT <FIELDS/>
        FROM <TABLE/>
        WHERE <FIELD name='period'/> = ${period} 
        <IF type='NE' field='start-minute-order' value='-1'>
			AND  <FIELD name='minute-order'/> >= ${start-minute-order}
		</IF>
		<IF type='NE' field='end-minute-order' value='-1'>
			AND  <FIELD name='minute-order'/> <= ${end-minute-order}
		</IF> 
        <IF type='NE' field='city' value='-1'>
			AND  <FIELD name='city'/> = ${city}
		</IF>
        <IF type='NE' field='operator' value='-1'>
			AND  <FIELD name='operator'/> = ${operator}
		</IF>
        <IF type='NE' field='network' value='-1'>
			AND  <FIELD name='network'/> = ${network}
		</IF>
		<IF type='NE' field='platform' value='-1'>
			AND  <FIELD name='platform'/> = ${platform}
		</IF>
		<IF type='NE' field='source' value='-1'>
			AND  <FIELD name='source'/> = ${source}
		</IF>
        group by  <FIELD name='operator'/>  ]]></statement>
      </query>
      <query name="find-data-by-source" type="SELECT" multiple="true">
        <param name="speed-id" />
        <param name="period" />
        <param name="city" />
        <param name="operator" />
        <param name="network" />
        <param name="platform" />
        <param name="source" />
        <param name="start-minute-order" />
        <param name="end-minute-order" />
        <statement><![CDATA[SELECT <FIELDS/>
        FROM <TABLE/>
        WHERE <FIELD name='period'/> = ${period} 
        <IF type='NE' field='start-minute-order' value='-1'>
			AND  <FIELD name='minute-order'/> >= ${start-minute-order}
		</IF>
		<IF type='NE' field='end-minute-order' value='-1'>
			AND  <FIELD name='minute-order'/> <= ${end-minute-order}
		</IF> 
        <IF type='NE' field='city' value='-1'>
			AND  <FIELD name='city'/> = ${city}
		</IF>
        <IF type='NE' field='operator' value='-1'>
			AND  <FIELD name='operator'/> = ${operator}
		</IF>
        <IF type='NE' field='network' value='-1'>
			AND  <FIELD name='network'/> = ${network}
		</IF>
		<IF type='NE' field='platform' value='-1'>
			AND  <FIELD name='platform'/> = ${platform}
		</IF>
		<IF type='NE' field='source' value='-1'>
			AND  <FIELD name='source'/> = ${source}
		</IF>
        group by  <FIELD name='source'/>  ]]></statement>
      </query>
     <query name="find-data-by-network" type="SELECT" multiple="true">
        <param name="speed-id" />
        <param name="period" />
        <param name="city" />
        <param name="operator" />
        <param name="network" />
        <param name="platform" />
        <param name="source" />
        <param name="start-minute-order" />
        <param name="end-minute-order" />
        <statement><![CDATA[SELECT <FIELDS/>
        FROM <TABLE/>
        WHERE <FIELD name='period'/> = ${period} 
        <IF type='NE' field='start-minute-order' value='-1'>
			AND  <FIELD name='minute-order'/> >= ${start-minute-order}
		</IF>
		<IF type='NE' field='end-minute-order' value='-1'>
			AND  <FIELD name='minute-order'/> <= ${end-minute-order}
		</IF> 
        <IF type='NE' field='city' value='-1'>
			AND  <FIELD name='city'/> = ${city}
		</IF>
        <IF type='NE' field='operator' value='-1'>
			AND  <FIELD name='operator'/> = ${operator}
		</IF>
        <IF type='NE' field='network' value='-1'>
			AND  <FIELD name='network'/> = ${network}
		</IF>
		<IF type='NE' field='platform' value='-1'>
			AND  <FIELD name='platform'/> = ${platform}
		</IF>
		<IF type='NE' field='source' value='-1'>
			AND  <FIELD name='source'/> = ${source}
		</IF>
        group by  <FIELD name='network'/> ]]></statement>
      </query>
		</query-defs>
	</entity>
</entities>

