<?xml version="1.0" encoding="utf-8"?>
<company>
   <product-line id="mkt-get-items" order="0.0" title="mkt-get-items" metric-dashboard="false" application-dashboard="false" network-dashboard="false" system-monitor-dashboard="false" user-monitor-dashboard="true" database-monitor-dashboard="false">
      <domain id="broker-service"/>
   </product-line>
   <product-line id="searchshop" order="0.0" title="searchshop" metric-dashboard="false" application-dashboard="false" network-dashboard="false" system-monitor-dashboard="false" user-monitor-dashboard="true" database-monitor-dashboard="false">
      <domain id="broker-service"/>
   </product-line>
   <product-line id="homepagefindtab.bin" order="0.0" title="homepagefindtab.bin" metric-dashboard="false" application-dashboard="false" network-dashboard="false" system-monitor-dashboard="false" user-monitor-dashboard="true" database-monitor-dashboard="false">
      <domain id="broker-service"/>
   </product-line>
   <product-line id="homepagedealgn" order="0.0" title="homepagedealgn" metric-dashboard="false" application-dashboard="false" network-dashboard="false" system-monitor-dashboard="false" user-monitor-dashboard="true" database-monitor-dashboard="false">
      <domain id="broker-service"/>
   </product-line>
   <product-line id="rgc" order="0.0" title="rgc" metric-dashboard="false" application-dashboard="false" network-dashboard="false" system-monitor-dashboard="false" user-monitor-dashboard="true" database-monitor-dashboard="false">
      <domain id="broker-service"/>
   </product-line>
   <product-line id="dpindex-userinfo" order="0.0" title="dpindex-userinfo" metric-dashboard="false" application-dashboard="false" network-dashboard="false" system-monitor-dashboard="false" user-monitor-dashboard="true" database-monitor-dashboard="false">
      <domain id="broker-service"/>
   </product-line>
   <product-line id="test" order="0.0" title="test" metric-dashboard="false" application-dashboard="false" network-dashboard="false" system-monitor-dashboard="false" user-monitor-dashboard="true" database-monitor-dashboard="false">
      <domain id="broker-service"/>
   </product-line>
   <product-line id="index-getNewItem" order="0.0" title="index-getNewItem" metric-dashboard="false" application-dashboard="false" network-dashboard="false" system-monitor-dashboard="false" user-monitor-dashboard="true" database-monitor-dashboard="false">
      <domain id="broker-service"/>
   </product-line>
   <product-line id="index-userinfo" order="0.0" title="index-userinfo" metric-dashboard="false" application-dashboard="false" network-dashboard="false" system-monitor-dashboard="false" user-monitor-dashboard="true" database-monitor-dashboard="false">
      <domain id="broker-service"/>
   </product-line>
   <product-line id="mobile-shop" order="0.0" title="mobile-shop" metric-dashboard="false" application-dashboard="false" network-dashboard="false" system-monitor-dashboard="false" user-monitor-dashboard="true" database-monitor-dashboard="false">
      <domain id="broker-service"/>
   </product-line>
   <product-line id="s2-middle-tcpConnect" order="0.0" title="s2-middle-tcpConnect" metric-dashboard="false" application-dashboard="false" network-dashboard="false" system-monitor-dashboard="false" user-monitor-dashboard="true" database-monitor-dashboard="false">
      <domain id="broker-service"/>
   </product-line>
   <product-line id="s2-middle-request" order="0.0" title="s2-middle-request" metric-dashboard="false" application-dashboard="false" network-dashboard="false" system-monitor-dashboard="false" user-monitor-dashboard="true" database-monitor-dashboard="false">
      <domain id="broker-service"/>
   </product-line>
   <product-line id="s2-large-dnsLookup" order="0.0" title="s2-large-dnsLookup" metric-dashboard="false" application-dashboard="false" network-dashboard="false" system-monitor-dashboard="false" user-monitor-dashboard="true" database-monitor-dashboard="false">
      <domain id="broker-service"/>
   </product-line>
   <product-line id="s2-large-request" order="0.0" title="s2-large-request" metric-dashboard="false" application-dashboard="false" network-dashboard="false" system-monitor-dashboard="false" user-monitor-dashboard="true" database-monitor-dashboard="false">
      <domain id="broker-service"/>
   </product-line>
   <product-line id="s2-small-response" order="0.0" title="s2-small-response" metric-dashboard="false" application-dashboard="false" network-dashboard="false" system-monitor-dashboard="false" user-monitor-dashboard="true" database-monitor-dashboard="false">
      <domain id="broker-service"/>
   </product-line>
   <product-line id="s2-middle-dnsLookup" order="0.0" title="s2-middle-dnsLookup" metric-dashboard="false" application-dashboard="false" network-dashboard="false" system-monitor-dashboard="false" user-monitor-dashboard="true" database-monitor-dashboard="false">
      <domain id="broker-service"/>
   </product-line>
   <product-line id="s2-middle-response" order="0.0" title="s2-middle-response" metric-dashboard="false" application-dashboard="false" network-dashboard="false" system-monitor-dashboard="false" user-monitor-dashboard="true" database-monitor-dashboard="false">
      <domain id="broker-service"/>
   </product-line>
   <product-line id="s2-small-dnsLookup" order="0.0" title="s2-small-dnsLookup" metric-dashboard="false" application-dashboard="false" network-dashboard="false" system-monitor-dashboard="false" user-monitor-dashboard="true" database-monitor-dashboard="false">
      <domain id="broker-service"/>
   </product-line>
   <product-line id="s2-small-tcpConnect" order="0.0" title="s2-small-tcpConnect" metric-dashboard="false" application-dashboard="false" network-dashboard="false" system-monitor-dashboard="false" user-monitor-dashboard="true" database-monitor-dashboard="false">
      <domain id="broker-service"/>
   </product-line>
   <product-line id="s2-small-request" order="0.0" title="s2-small-request" metric-dashboard="false" application-dashboard="false" network-dashboard="false" system-monitor-dashboard="false" user-monitor-dashboard="true" database-monitor-dashboard="false">
      <domain id="broker-service"/>
   </product-line>
   <product-line id="s2-large-response" order="0.0" title="s2-large-response" metric-dashboard="false" application-dashboard="false" network-dashboard="false" system-monitor-dashboard="false" user-monitor-dashboard="true" database-monitor-dashboard="false">
      <domain id="broker-service"/>
   </product-line>
   <product-line id="s2-large-tcpConnect" order="0.0" title="s2-large-tcpConnect" metric-dashboard="false" application-dashboard="false" network-dashboard="false" system-monitor-dashboard="false" user-monitor-dashboard="true" database-monitor-dashboard="false">
      <domain id="broker-service"/>
   </product-line>
   <product-line id="s3-middle-tcpConnect" order="0.0" title="s3-middle-tcpConnect" metric-dashboard="false" application-dashboard="false" network-dashboard="false" system-monitor-dashboard="false" user-monitor-dashboard="true" database-monitor-dashboard="false">
      <domain id="broker-service"/>
   </product-line>
   <product-line id="s3-middle-response" order="0.0" title="s3-middle-response" metric-dashboard="false" application-dashboard="false" network-dashboard="false" system-monitor-dashboard="false" user-monitor-dashboard="true" database-monitor-dashboard="false">
      <domain id="broker-service"/>
   </product-line>
   <product-line id="s3-middle-dnsLookup" order="0.0" title="s3-middle-dnsLookup" metric-dashboard="false" application-dashboard="false" network-dashboard="false" system-monitor-dashboard="false" user-monitor-dashboard="true" database-monitor-dashboard="false">
      <domain id="broker-service"/>
   </product-line>
   <product-line id="s3-small-tcpConnect" order="0.0" title="s3-small-tcpConnect" metric-dashboard="false" application-dashboard="false" network-dashboard="false" system-monitor-dashboard="false" user-monitor-dashboard="true" database-monitor-dashboard="false">
      <domain id="broker-service"/>
   </product-line>
   <product-line id="s3-large-request" order="0.0" title="s3-large-request" metric-dashboard="false" application-dashboard="false" network-dashboard="false" system-monitor-dashboard="false" user-monitor-dashboard="true" database-monitor-dashboard="false">
      <domain id="broker-service"/>
   </product-line>
   <product-line id="s3-small-request" order="0.0" title="s3-small-request" metric-dashboard="false" application-dashboard="false" network-dashboard="false" system-monitor-dashboard="false" user-monitor-dashboard="true" database-monitor-dashboard="false">
      <domain id="broker-service"/>
   </product-line>
   <product-line id="s3-large-dnsLookup" order="0.0" title="s3-large-dnsLookup" metric-dashboard="false" application-dashboard="false" network-dashboard="false" system-monitor-dashboard="false" user-monitor-dashboard="true" database-monitor-dashboard="false">
      <domain id="broker-service"/>
   </product-line>
   <product-line id="s3-large-response" order="0.0" title="s3-large-response" metric-dashboard="false" application-dashboard="false" network-dashboard="false" system-monitor-dashboard="false" user-monitor-dashboard="true" database-monitor-dashboard="false">
      <domain id="broker-service"/>
   </product-line>
   <product-line id="s3-small-dnsLookup" order="0.0" title="s3-small-dnsLookup" metric-dashboard="false" application-dashboard="false" network-dashboard="false" system-monitor-dashboard="false" user-monitor-dashboard="true" database-monitor-dashboard="false">
      <domain id="broker-service"/>
   </product-line>
   <product-line id="s3-small-response" order="0.0" title="s3-small-response" metric-dashboard="false" application-dashboard="false" network-dashboard="false" system-monitor-dashboard="false" user-monitor-dashboard="true" database-monitor-dashboard="false">
      <domain id="broker-service"/>
   </product-line>
   <product-line id="s3-large-tcpConnect" order="0.0" title="s3-large-tcpConnect" metric-dashboard="false" application-dashboard="false" network-dashboard="false" system-monitor-dashboard="false" user-monitor-dashboard="true" database-monitor-dashboard="false">
      <domain id="broker-service"/>
   </product-line>
   <product-line id="s3-middle-request" order="0.0" title="s3-middle-request" metric-dashboard="false" application-dashboard="false" network-dashboard="false" system-monitor-dashboard="false" user-monitor-dashboard="true" database-monitor-dashboard="false">
      <domain id="broker-service"/>
   </product-line>
   <product-line id="s1-middle-request" order="0.0" title="s1-middle-request" metric-dashboard="false" application-dashboard="false" network-dashboard="false" system-monitor-dashboard="false" user-monitor-dashboard="true" database-monitor-dashboard="false">
      <domain id="broker-service"/>
   </product-line>
   <product-line id="s1-middle-tcpConnect" order="0.0" title="s1-middle-tcpConnect" metric-dashboard="false" application-dashboard="false" network-dashboard="false" system-monitor-dashboard="false" user-monitor-dashboard="true" database-monitor-dashboard="false">
      <domain id="broker-service"/>
   </product-line>
   <product-line id="s1-middle-dnsLookup" order="0.0" title="s1-middle-dnsLookup" metric-dashboard="false" application-dashboard="false" network-dashboard="false" system-monitor-dashboard="false" user-monitor-dashboard="true" database-monitor-dashboard="false">
      <domain id="broker-service"/>
   </product-line>
   <product-line id="s1-large-request" order="0.0" title="s1-large-request" metric-dashboard="false" application-dashboard="false" network-dashboard="false" system-monitor-dashboard="false" user-monitor-dashboard="true" database-monitor-dashboard="false">
      <domain id="broker-service"/>
   </product-line>
   <product-line id="s1-large-tcpConnect" order="0.0" title="s1-large-tcpConnect" metric-dashboard="false" application-dashboard="false" network-dashboard="false" system-monitor-dashboard="false" user-monitor-dashboard="true" database-monitor-dashboard="false">
      <domain id="broker-service"/>
   </product-line>
   <product-line id="s1-middle-response" order="0.0" title="s1-middle-response" metric-dashboard="false" application-dashboard="false" network-dashboard="false" system-monitor-dashboard="false" user-monitor-dashboard="true" database-monitor-dashboard="false">
      <domain id="broker-service"/>
   </product-line>
   <product-line id="s1-large-response" order="0.0" title="s1-large-response" metric-dashboard="false" application-dashboard="false" network-dashboard="false" system-monitor-dashboard="false" user-monitor-dashboard="true" database-monitor-dashboard="false">
      <domain id="broker-service"/>
   </product-line>
   <product-line id="s1-small-response" order="0.0" title="s1-small-response" metric-dashboard="false" application-dashboard="false" network-dashboard="false" system-monitor-dashboard="false" user-monitor-dashboard="true" database-monitor-dashboard="false">
      <domain id="broker-service"/>
   </product-line>
   <product-line id="s1-small-dnsLookup" order="0.0" title="s1-small-dnsLookup" metric-dashboard="false" application-dashboard="false" network-dashboard="false" system-monitor-dashboard="false" user-monitor-dashboard="true" database-monitor-dashboard="false">
      <domain id="broker-service"/>
   </product-line>
   <product-line id="s1-large-dnsLookup" order="0.0" title="s1-large-dnsLookup" metric-dashboard="false" application-dashboard="false" network-dashboard="false" system-monitor-dashboard="false" user-monitor-dashboard="true" database-monitor-dashboard="false">
      <domain id="broker-service"/>
   </product-line>
   <product-line id="s1-small-tcpConnect" order="0.0" title="s1-small-tcpConnect" metric-dashboard="false" application-dashboard="false" network-dashboard="false" system-monitor-dashboard="false" user-monitor-dashboard="true" database-monitor-dashboard="false">
      <domain id="broker-service"/>
   </product-line>
   <product-line id="verifyOrder" order="0.0" title="verifyOrder" metric-dashboard="false" application-dashboard="false" network-dashboard="false" system-monitor-dashboard="false" user-monitor-dashboard="true" database-monitor-dashboard="false">
      <domain id="broker-service"/>
   </product-line>
   <product-line id="cityguidebanner" order="0.0" title="cityguidebanner" metric-dashboard="false" application-dashboard="false" network-dashboard="false" system-monitor-dashboard="false" user-monitor-dashboard="true" database-monitor-dashboard="false">
      <domain id="broker-service"/>
   </product-line>
   <product-line id="shopweb-suggestShop" order="0.0" title="shopweb-suggestShop" metric-dashboard="false" application-dashboard="false" network-dashboard="false" system-monitor-dashboard="false" user-monitor-dashboard="true" database-monitor-dashboard="false">
      <domain id="broker-service"/>
   </product-line>
   <product-line id="yuding-shopweb-timeout" order="0.0" title="yuding-shopweb-timeout" metric-dashboard="false" application-dashboard="false" network-dashboard="false" system-monitor-dashboard="false" user-monitor-dashboard="true" database-monitor-dashboard="false">
      <domain id="broker-service"/>
   </product-line>
   <product-line id="yuding-shopweb" order="0.0" title="yuding-shopweb" metric-dashboard="false" application-dashboard="false" network-dashboard="false" system-monitor-dashboard="false" user-monitor-dashboard="true" database-monitor-dashboard="false">
      <domain id="broker-service"/>
   </product-line>
   <product-line id="cookiemonster-www" order="0.0" title="cookiemonster-www" metric-dashboard="false" application-dashboard="false" network-dashboard="false" system-monitor-dashboard="false" user-monitor-dashboard="true" database-monitor-dashboard="false">
      <domain id="broker-service"/>
   </product-line>
   <product-line id="midas-cpm" order="0.0" title="midas-cpm" metric-dashboard="false" application-dashboard="false" network-dashboard="false" system-monitor-dashboard="false" user-monitor-dashboard="true" database-monitor-dashboard="false">
      <domain id="broker-service"/>
   </product-line>
   <product-line id="midas-cpm-ajax" order="0.0" title="midas-cpm-ajax" metric-dashboard="false" application-dashboard="false" network-dashboard="false" system-monitor-dashboard="false" user-monitor-dashboard="true" database-monitor-dashboard="false">
      <domain id="broker-service"/>
   </product-line>
   <product-line id="qzone-feedlist" order="0.0" title="qzone-feedlist" metric-dashboard="false" application-dashboard="false" network-dashboard="false" system-monitor-dashboard="false" user-monitor-dashboard="true" database-monitor-dashboard="false">
      <domain id="broker-service"/>
   </product-line>
   <product-line id="midas-cpm-ajax2" order="0.0" title="midas-cpm-ajax2" metric-dashboard="false" application-dashboard="false" network-dashboard="false" system-monitor-dashboard="false" user-monitor-dashboard="true" database-monitor-dashboard="false">
      <domain id="broker-service"/>
   </product-line>
   <product-line id="pic-upload" order="0.0" title="pic-upload" metric-dashboard="false" application-dashboard="false" network-dashboard="false" system-monitor-dashboard="false" user-monitor-dashboard="true" database-monitor-dashboard="false">
      <domain id="broker-service"/>
   </product-line>
   <product-line id="photos-list" order="0.0" title="photos-list" metric-dashboard="false" application-dashboard="false" network-dashboard="false" system-monitor-dashboard="false" user-monitor-dashboard="true" database-monitor-dashboard="false">
      <domain id="broker-service"/>
   </product-line>
   <product-line id="photo-single" order="0.0" title="photo-single" metric-dashboard="false" application-dashboard="false" network-dashboard="false" system-monitor-dashboard="false" user-monitor-dashboard="true" database-monitor-dashboard="false">
      <domain id="broker-service"/>
   </product-line>
   <product-line id="photo-shop-page" order="0.0" title="photo-shop-page" metric-dashboard="false" application-dashboard="false" network-dashboard="false" system-monitor-dashboard="false" user-monitor-dashboard="true" database-monitor-dashboard="false">
      <domain id="broker-service"/>
   </product-line>
   <product-line id="photo-search-list" order="0.0" title="photo-search-list" metric-dashboard="false" application-dashboard="false" network-dashboard="false" system-monitor-dashboard="false" user-monitor-dashboard="true" database-monitor-dashboard="false">
      <domain id="broker-service"/>
   </product-line>
   <product-line id="reserve-bookable" order="0.0" title="reserve-bookable" metric-dashboard="false" application-dashboard="false" network-dashboard="false" system-monitor-dashboard="false" user-monitor-dashboard="true" database-monitor-dashboard="false">
      <domain id="broker-service"/>
   </product-line>
   <product-line id="reserve-win" order="0.0" title="reserve-win" metric-dashboard="false" application-dashboard="false" network-dashboard="false" system-monitor-dashboard="false" user-monitor-dashboard="true" database-monitor-dashboard="false">
      <domain id="broker-service"/>
   </product-line>
   <product-line id="reserve-available" order="0.0" title="reserve-available" metric-dashboard="false" application-dashboard="false" network-dashboard="false" system-monitor-dashboard="false" user-monitor-dashboard="true" database-monitor-dashboard="false">
      <domain id="broker-service"/>
   </product-line>
   <product-line id="reserve-check" order="0.0" title="reserve-check" metric-dashboard="false" application-dashboard="false" network-dashboard="false" system-monitor-dashboard="false" user-monitor-dashboard="true" database-monitor-dashboard="false">
      <domain id="broker-service"/>
   </product-line>
   <product-line id="submit-order" order="0.0" title="submit-order" metric-dashboard="false" application-dashboard="false" network-dashboard="false" system-monitor-dashboard="false" user-monitor-dashboard="true" database-monitor-dashboard="false">
      <domain id="broker-service"/>
   </product-line>
   <product-line id="ugc-add-review" order="0.0" title="ugc-add-review" metric-dashboard="false" application-dashboard="false" network-dashboard="false" system-monitor-dashboard="false" user-monitor-dashboard="true" database-monitor-dashboard="false">
      <domain id="broker-service"/>
   </product-line>
   <product-line id="m-geo-html5" order="0.0" title="m-geo-html5" metric-dashboard="false" application-dashboard="false" network-dashboard="false" system-monitor-dashboard="false" user-monitor-dashboard="true" database-monitor-dashboard="false">
      <domain id="broker-service"/>
   </product-line>
   <product-line id="m-geo-weixin" order="0.0" title="m-geo-weixin" metric-dashboard="false" application-dashboard="false" network-dashboard="false" system-monitor-dashboard="false" user-monitor-dashboard="true" database-monitor-dashboard="false">
      <domain id="broker-service"/>
   </product-line>
   <product-line id="m-geo-html5-timeout" order="0.0" title="m-geo-html5-timeout" metric-dashboard="false" application-dashboard="false" network-dashboard="false" system-monitor-dashboard="false" user-monitor-dashboard="true" database-monitor-dashboard="false">
      <domain id="broker-service"/>
   </product-line>
   <product-line id="m-geo-weixin-timeout" order="0.0" title="m-geo-weixin-timeout" metric-dashboard="false" application-dashboard="false" network-dashboard="false" system-monitor-dashboard="false" user-monitor-dashboard="true" database-monitor-dashboard="false">
      <domain id="broker-service"/>
   </product-line>
   <product-line id="m-performance-index-onload" order="0.0" title="m-performance-index-onload" metric-dashboard="false" application-dashboard="false" network-dashboard="false" system-monitor-dashboard="false" user-monitor-dashboard="true" database-monitor-dashboard="false">
      <domain id="broker-service"/>
   </product-line>
   <product-line id="m-weixin-bank-pay-call" order="0.0" title="m-weixin-bank-pay-call" metric-dashboard="false" application-dashboard="false" network-dashboard="false" system-monitor-dashboard="false" user-monitor-dashboard="true" database-monitor-dashboard="false">
      <domain id="broker-service"/>
   </product-line>
   <product-line id="m-weixin-bank-pay-button" order="0.0" title="m-weixin-bank-pay-button" metric-dashboard="false" application-dashboard="false" network-dashboard="false" system-monitor-dashboard="false" user-monitor-dashboard="true" database-monitor-dashboard="false">
      <domain id="broker-service"/>
   </product-line>
   <product-line id="open-qq-order-thirdpartylogin" order="0.0" title="open-qq-order-thirdpartylogin" metric-dashboard="false" application-dashboard="false" network-dashboard="false" system-monitor-dashboard="false" user-monitor-dashboard="true" database-monitor-dashboard="false">
      <domain id="broker-service"/>
   </product-line>
   <product-line id="open-qq-order-mobiledynamiclogin" order="0.0" title="open-qq-order-mobiledynamiclogin" metric-dashboard="false" application-dashboard="false" network-dashboard="false" system-monitor-dashboard="false" user-monitor-dashboard="true" database-monitor-dashboard="false">
      <domain id="broker-service"/>
   </product-line>
   <product-line id="open-qq-order-bindphone" order="0.0" title="open-qq-order-bindphone" metric-dashboard="false" application-dashboard="false" network-dashboard="false" system-monitor-dashboard="false" user-monitor-dashboard="true" database-monitor-dashboard="false">
      <domain id="broker-service"/>
   </product-line>
   <product-line id="pic-upload-addreviewlist" order="0.0" title="pic-upload-addreviewlist" metric-dashboard="false" application-dashboard="false" network-dashboard="false" system-monitor-dashboard="false" user-monitor-dashboard="true" database-monitor-dashboard="false">
      <domain id="broker-service"/>
   </product-line>
   <product-line id="card-detail" order="0.0" title="card-detail" metric-dashboard="false" application-dashboard="false" network-dashboard="false" system-monitor-dashboard="false" user-monitor-dashboard="true" database-monitor-dashboard="false">
      <domain id="broker-service"/>
   </product-line>
   <product-line id="card-join" order="0.0" title="card-join" metric-dashboard="false" application-dashboard="false" network-dashboard="false" system-monitor-dashboard="false" user-monitor-dashboard="true" database-monitor-dashboard="false">
      <domain id="broker-service"/>
   </product-line>
   <product-line id="card-joinSubmit" order="0.0" title="card-joinSubmit" metric-dashboard="false" application-dashboard="false" network-dashboard="false" system-monitor-dashboard="false" user-monitor-dashboard="true" database-monitor-dashboard="false">
      <domain id="broker-service"/>
   </product-line>
   <product-line id="card-getVerify" order="0.0" title="card-getVerify" metric-dashboard="false" application-dashboard="false" network-dashboard="false" system-monitor-dashboard="false" user-monitor-dashboard="true" database-monitor-dashboard="false">
      <domain id="broker-service"/>
   </product-line>
</company>
